cropper.py
pycropper-0.1.8.dist-info/METADATA
pycropper-0.1.8.dist-info/WHEEL
pycropper-0.1.8.dist-info/entry_points.txt
pycropper-0.1.8.dist-info/top_level.txt
pycropper-0.1.8.dist-info/RECORD
