Metadata-Version: 2.4
Name: pycropper
Version: 0.1.8
Summary: Auto-crop images
Author-email: Shoji SZGZ <mr.szgz@gmail.com>
Project-URL: Homepage, https://github.com/mr-szgz/py-cropper
Project-URL: Repository, https://github.com/mr-szgz/py-cropper
Classifier: Development Status :: 4 - Beta
Classifier: Intended Audience :: End Users/Desktop
Classifier: License :: OSI Approved :: MIT License
Classifier: Programming Language :: Python :: 3.10
Classifier: Programming Language :: Python :: 3.11
Classifier: Programming Language :: Python :: 3.12
Requires-Python: >=3.8
Requires-Dist: Pillow
Requires-Dist: typer
Provides-Extra: dev
Requires-Dist: pytest; extra == "dev"
Requires-Dist: bump2version; extra == "dev"
